{
  "id": "4046926",
  "name": "index3",
  "font_family": "iconfont",
  "css_prefix_text": "icon-",
  "description": "",
  "glyphs": [
    {
      "icon_id": "11372639",
      "name": "爱心",
      "font_class": "aixin",
      "unicode": "e8ab",
      "unicode_decimal": 59563
    },
    {
      "icon_id": "11372640",
      "name": "编辑",
      "font_class": "bianji",
      "unicode": "e8ac",
      "unicode_decimal": 59564
    },
    {
      "icon_id": "11372643",
      "name": "安全",
      "font_class": "anquan",
      "unicode": "e8ad",
      "unicode_decimal": 59565
    },
    {
      "icon_id": "11372644",
      "name": "帮助",
      "font_class": "bangzhu",
      "unicode": "e8ae",
      "unicode_decimal": 59566
    },
    {
      "icon_id": "11372646",
      "name": "播放记录",
      "font_class": "bofangjilu",
      "unicode": "e8af",
      "unicode_decimal": 59567
    },
    {
      "icon_id": "11372651",
      "name": "点赞",
      "font_class": "dianzan",
      "unicode": "e8b0",
      "unicode_decimal": 59568
    },
    {
      "icon_id": "11372666",
      "name": "分享",
      "font_class": "fenxiang",
      "unicode": "e8b1",
      "unicode_decimal": 59569
    },
    {
      "icon_id": "11372668",
      "name": "会员",
      "font_class": "huiyuan",
      "unicode": "e8b2",
      "unicode_decimal": 59570
    },
    {
      "icon_id": "11372685",
      "name": "扫一扫",
      "font_class": "saoyisao",
      "unicode": "e8b5",
      "unicode_decimal": 59573
    },
    {
      "icon_id": "11372693",
      "name": "删除",
      "font_class": "shanchu",
      "unicode": "e8b6",
      "unicode_decimal": 59574
    }
  ]
}
